MANIFEST.in
README.rst
setup.py
rpi_rf/__init__.py
rpi_rf/rpi_rf.py
rpi_rf.egg-info/PKG-INFO
rpi_rf.egg-info/SOURCES.txt
rpi_rf.egg-info/dependency_links.txt
rpi_rf.egg-info/requires.txt
rpi_rf.egg-info/top_level.txt