Metadata-Version: 1.1
Name: rpi-rf
Version: 0.9.2
Summary: Sending and receiving 433Mhz signals with cheap GPIO RF modules a Raspberry Pi
Home-page: https://github.com/milaq/rpi-rf
Author: Micha LaQua
Author-email: micha.laqua@gmail.com
License: BSD
Keywords: rpi,raspberry,raspberry pi,rf,gpio,radio,433,433mhz
Platform: UNKNOWN
Classifier: Development Status :: 4 - Beta
Classifier: Intended Audience :: Developers
Classifier: Topic :: Software Development :: Build Tools
Classifier: License :: OSI Approved :: BSD License
Classifier: Programming Language :: Python :: 3
Classifier: Operating System :: POSIX :: Linux
Classifier: Topic :: Software Development :: Libraries :: Python Modules
